zense/__init__.py
zense-0.0.2.dist-info/METADATA
zense-0.0.2.dist-info/WHEEL
zense-0.0.2.dist-info/RECORD
