Metadata-Version: 2.4
Name: zense
Version: 0.0.2
Summary: Lightweight web stack
Project-URL: Source, https://github.com/zensical/zense
License: MIT
